pyisy/__init__.py
pyisy/clock.py
pyisy/configuration.py
pyisy/connection.py
pyisy/constants.py
pyisy/eventreader.py
pyisy/events.py
pyisy/helpers.py
pyisy/isy.py
pyisy/networking.py
pyisy/strings.py
pyisy/nodes/__init__.py
pyisy/nodes/group.py
pyisy/nodes/node.py
pyisy/nodes/nodebase.py
pyisy/programs/__init__.py
pyisy/programs/folder.py
pyisy/programs/program.py
pyisy/variables/__init__.py
pyisy/variables/variable.py
pyisy_beta-2.0.2.dist-info/LICENSE.txt
pyisy_beta-2.0.2.dist-info/METADATA
pyisy_beta-2.0.2.dist-info/WHEEL
pyisy_beta-2.0.2.dist-info/top_level.txt
pyisy_beta-2.0.2.dist-info/RECORD
