Metadata-Version: 2.1
Name: pyisy-beta
Version: 2.0.2
Summary: Python module to talk to ISY994 from UDI.
Home-page: https://github.com/automicus/PyISY
Author: Ryan Kraus
Author-email: automicus@gmail.com
License: Apache License 2.0
Keywords: home automation,isy,isy994,isy-994,UDI
Platform: any
Classifier: Intended Audience :: Developers
Classifier: License :: OSI Approved :: Apache Software License
Classifier: Operating System :: OS Independent
Classifier: Programming Language :: Python
Classifier: Programming Language :: Python :: 3
Classifier: Topic :: Software Development :: Libraries :: Python Modules
Requires-Dist: requests
